[
  { "emoji": "", "name": "转" },
  { "emoji": "", "name": "驻专住拽  拽专" },
  { "emoji": "", "name": "爪 驻砖" },
  { "emoji": "", "name": "爪 专拽" },
  { "emoji": "", "name": "转 注" },
  { "emoji": "", "name": "" },
  { "emoji": "", "name": "砖" },
  { "emoji": "", "name": "转 专拽" },
  { "emoji": "", "name": "专 注 拽拽 转" },
  { "emoji": "", "name": " 砖驻  " },
  { "emoji": "Ш", "name": "转 驻专转  住 爪专 注爪" },
  { "emoji": "", "name": "住 专 爪爪转 转" },
  { "emoji": "ガ", "name": "注 驻 " },
  { "emoji": "", "name": "注" },
  { "emoji": "", "name": "砖/ 拽砖" },
  { "emoji": "ゥ", "name": "砖 转 拽拽" },
  { "emoji": "", "name": "砖 住" },
  { "emoji": "", "name": "转转" },
  { "emoji": "", "name": "转驻" },
  { "emoji": "", "name": "转驻" }
]
